xoverturning/__init__.py
xoverturning/compfunc.py
xoverturning/moc.py
xoverturning-0.0.1.dist-info/METADATA
xoverturning-0.0.1.dist-info/WHEEL
xoverturning-0.0.1.dist-info/top_level.txt
xoverturning-0.0.1.dist-info/RECORD
